_pynvx.cpython-39-darwin.so
pynvx/__init__.py
pynvx/pynvml.py
pynvx-1.0.0.dist-info/LICENSE
pynvx-1.0.0.dist-info/METADATA
pynvx-1.0.0.dist-info/WHEEL
pynvx-1.0.0.dist-info/top_level.txt
pynvx-1.0.0.dist-info/RECORD
